uniphi/__init__.py
uniphi/aesCipher.py
uniphi/common.py
uniphi/constants.py
uniphi/exceptions.py
uniphi/sqlalchemy_uniphi.py
uniphi/typeId.py
uniphi/uniphi.py
uniphi-0.1.64.dist-info/METADATA
uniphi-0.1.64.dist-info/WHEEL
uniphi-0.1.64.dist-info/entry_points.txt
uniphi-0.1.64.dist-info/top_level.txt
uniphi-0.1.64.dist-info/RECORD
