Metadata-Version: 2.1
Name: uniphi
Version: 0.1.64
Summary: UNKNOWN
Home-page: UNKNOWN
Author: Uniphi, Inc.
Author-email: adishesh@uniphi.it
License: UNKNOWN
Platform: UNKNOWN
Classifier: Operating System :: POSIX :: Linux
Classifier: License :: OSI Approved :: MIT License
Classifier: Programming Language :: Python :: 3.5
Classifier: Programming Language :: Python :: 3.6
Classifier: Programming Language :: Python :: 3.7
Requires-Dist: sqlalchemy (>=1.0.0)
Requires-Dist: future
Requires-Dist: python-dateutil
Requires-Dist: pycryptodome
